maildaemon/__init__.py
maildaemon/__main__.py
maildaemon/_version.py
maildaemon/config.py
maildaemon/connection.py
maildaemon/connection_group.py
maildaemon/daemon.py
maildaemon/daemon_group.py
maildaemon/email_cache.py
maildaemon/filter_actions.py
maildaemon/folder.py
maildaemon/gmail_imap_daemon.py
maildaemon/imap_cache.py
maildaemon/imap_connection.py
maildaemon/message.py
maildaemon/message_filter.py
maildaemon/pop_cache.py
maildaemon/pop_connection.py
maildaemon/py.typed
maildaemon/smtp_connection.py
maildaemon/smtp_daemon.py
maildaemon-0.2.1.dist-info/LICENSE
maildaemon-0.2.1.dist-info/METADATA
maildaemon-0.2.1.dist-info/NOTICE
maildaemon-0.2.1.dist-info/WHEEL
maildaemon-0.2.1.dist-info/entry_points.txt
maildaemon-0.2.1.dist-info/top_level.txt
maildaemon-0.2.1.dist-info/RECORD
