Metadata-Version: 2.1
Name: maildaemon
Version: 0.2.1
Summary: Multi-server mail filtering daemon supporting IMAP, POP and SMTP.
Home-page: https://github.com/mbdevpl/maildaemon
Download-URL: 
Author: Mateusz Bysiek
Author-email: mateusz.bysiek@gmail.com
Maintainer: Mateusz Bysiek
Maintainer-email: mateusz.bysiek@gmail.com
License: Apache License 2.0
Keywords: e-mail,filter,daemon,imap,pop,smtp
Classifier: Development Status :: 1 - Planning
Classifier: Environment :: Console
Classifier: Intended Audience :: Developers
Classifier: License :: OSI Approved :: Apache Software License
Classifier: Natural Language :: English
Classifier: Operating System :: POSIX :: Linux
Classifier: Programming Language :: Python :: 3.11
Classifier: Programming Language :: Python :: 3 :: Only
Classifier: Topic :: Utilities
Classifier: Typing :: Typed
Requires-Python: >=3.11
License-File: LICENSE
License-File: NOTICE
Requires-Dist: boilerplates[logging] ~=1.0
Requires-Dist: colorama ~=0.4
Requires-Dist: encrypted-config ~=0.1
Requires-Dist: oauthlib[rsa] ~=3.2
Requires-Dist: ordered-set ~=4.1
Requires-Dist: python-daemon ~=3.0
Requires-Dist: python-dateutil ~=2.8
Requires-Dist: requests-oauthlib ~=1.3
Requires-Dist: timing ~=0.5
Requires-Dist: version-query ~=1.5
